fsforge/__init__.py
fsforge/_capture.py
fsforge/_forge.py
fsforge/_utils.py
fsforge-1.0.1.dist-info/LICENSE.txt
fsforge-1.0.1.dist-info/METADATA
fsforge-1.0.1.dist-info/WHEEL
fsforge-1.0.1.dist-info/top_level.txt
fsforge-1.0.1.dist-info/RECORD
