Metadata-Version: 2.1
Name: fsforge
Version: 1.0.1
Summary: Helper to create fake filesystem and quick capture its state (or state of a real one).
Home-page: https://gitlab.com/kamichal/fsforge
Author: Michał Kaczmarczyk
Author-email: michal.s.kaczmarczyk@gmail.com
License: Apache License v.2
Keywords: fsforge pyfakefs fs forged literal dict hard disk HDD snapshot in-memory test
Platform: UNKNOWN
Classifier: Operating System :: OS Independent
Classifier: License :: OSI Approved :: Apache Software License
Classifier: Topic :: System :: Monitoring
Classifier: Topic :: Software Development :: Testing
Classifier: Framework :: Pytest
Classifier: Programming Language :: Python :: 3
Classifier: Programming Language :: Python :: 3.6
Classifier: Programming Language :: Python :: 3.7
Classifier: Programming Language :: Python :: 3.8
Classifier: Programming Language :: Python :: 3.9
Classifier: Programming Language :: Python :: 3.10
Classifier: Programming Language :: Python :: Implementation :: PyPy
Classifier: Development Status :: 5 - Production/Stable
Classifier: Intended Audience :: Developers
License-File: LICENSE.txt
Requires-Dist: pyfakefs (==4.5.*)
